setup.py
logfigure/__init__.py
logfigure.egg-info/PKG-INFO
logfigure.egg-info/SOURCES.txt
logfigure.egg-info/dependency_links.txt
logfigure.egg-info/entry_points.txt
logfigure.egg-info/top_level.txt