Metadata-Version: 1.0
Name: logfigure
Version: 0.01
Summary: Logging configuration that respects your sanity
Home-page: https://github.com/afroisalreadyinu/logfigure
Author: Ulas Tuerkmen
Author-email: ulas.tuerkmen@gmail.com
License: UNKNOWN
Platform: UNKNOWN
